openfermion/__init__.py
openfermion/_compat.py
openfermion/_compat_test.py
openfermion/_version.py
openfermion/config.py
openfermion/conftest.py
openfermion/py.typed
openfermion/chem/__init__.py
openfermion/chem/chemical_series.py
openfermion/chem/chemical_series_test.py
openfermion/chem/molecular_data.py
openfermion/chem/molecular_data_test.py
openfermion/chem/pubchem.py
openfermion/chem/pubchem_test.py
openfermion/chem/reduced_hamiltonian.py
openfermion/chem/reduced_hamiltonian_test.py
openfermion/circuits/__init__.py
openfermion/circuits/lcu_util.py
openfermion/circuits/lcu_util_test.py
openfermion/circuits/low_rank.py
openfermion/circuits/low_rank_test.py
openfermion/circuits/slater_determinants.py
openfermion/circuits/slater_determinants_test.py
openfermion/circuits/trotter_exp_to_qgates.py
openfermion/circuits/trotter_exp_to_qgates_test.py
openfermion/circuits/unitary_cc.py
openfermion/circuits/unitary_cc_test.py
openfermion/circuits/vpe_circuits.py
openfermion/circuits/vpe_circuits_test.py
openfermion/circuits/gates/__init__.py
openfermion/circuits/gates/common_gates.py
openfermion/circuits/gates/common_gates_test.py
openfermion/circuits/gates/fermionic_simulation.py
openfermion/circuits/gates/fermionic_simulation_test.py
openfermion/circuits/gates/four_qubit_gates.py
openfermion/circuits/gates/four_qubit_gates_test.py
openfermion/circuits/gates/three_qubit_gates.py
openfermion/circuits/gates/three_qubit_gates_test.py
openfermion/circuits/primitives/__init__.py
openfermion/circuits/primitives/bogoliubov_transform.py
openfermion/circuits/primitives/bogoliubov_transform_test.py
openfermion/circuits/primitives/ffft.py
openfermion/circuits/primitives/ffft_test.py
openfermion/circuits/primitives/optimal_givens_decomposition.py
openfermion/circuits/primitives/optimal_givens_decomposition_test.py
openfermion/circuits/primitives/state_preparation.py
openfermion/circuits/primitives/state_preparation_test.py
openfermion/circuits/primitives/swap_network.py
openfermion-1.6.1.dist-info/AUTHORS
openfermion-1.6.1.dist-info/LICENSE
openfermion-1.6.1.dist-info/METADATA
openfermion-1.6.1.dist-info/NOTICE
openfermion-1.6.1.dist-info/WHEEL
openfermion-1.6.1.dist-info/top_level.txt
openfermion-1.6.1.dist-info/RECORD
