Metadata-Version: 2.1
Name: openfermion
Version: 1.6.1
Summary: The electronic structure package for quantum computers.
Home-page: http://www.openfermion.org
Author: The OpenFermion Developers
Author-email: help@openfermion.org
License: Apache 2
License-File: LICENSE
License-File: NOTICE
License-File: AUTHORS
Requires-Dist: cirq-core~=1.0
Requires-Dist: deprecation
Requires-Dist: h5py>=2.8
Requires-Dist: networkx
Requires-Dist: numpy>=1.11.0
Requires-Dist: pubchempy
Requires-Dist: requests>=2.18
Requires-Dist: scipy>=1.1.0
Requires-Dist: sympy
Provides-Extra: resources
Requires-Dist: pyscf; extra == "resources"
Requires-Dist: jax; extra == "resources"
Requires-Dist: jaxlib; extra == "resources"
Requires-Dist: ase; extra == "resources"
